<?xml version="1.0" encoding="UTF-8" standalone="yes"?>
<userdb xmlns="http://example.org/ticket" xmlns:xsi="http://www.w3.org/2001/XMLSchema-instance" xsi:schemaLocation="http://example.org/ticket ../schema/UListeSchema.xsd">
    <user>
        <id>1</id>
        <jabber>admin</jabber>
        <Vorname>Max</Vorname>
        <Nachname>Mustermann</Nachname>
        <Standort>CGN</Standort>
        <status>admin</status>
        <KnowHows>
            <KnowHow>Software</KnowHow>
        </KnowHows>
        <Tickets>
            <ticketId>3</ticketId>
            <ticketId>4</ticketId>
            <ticketId>6</ticketId>
            <ticketId>7</ticketId>
            <ticketId>8</ticketId>
            <ticketId>9</ticketId>
            <ticketId>10</ticketId>
            <ticketId>11</ticketId>
            <ticketId>12</ticketId>
            <ticketId>13</ticketId>
            <ticketId>14</ticketId>
            <ticketId>15</ticketId>
            <ticketId>16</ticketId>
            <ticketId>17</ticketId>
            <ticketId>18</ticketId>
            <ticketId>19</ticketId>
            <ticketId>20</ticketId>
            <ticketId>21</ticketId>
            <ticketId>22</ticketId>
            <ticketId>23</ticketId>
            <ticketId>24</ticketId>
            <ticketId>25</ticketId>
            <ticketId>26</ticketId>
            <ticketId>27</ticketId>
            <ticketId>28</ticketId>
            <ticketId>29</ticketId>
            <ticketId>30</ticketId>
            <ticketId>31</ticketId>
            <ticketId>32</ticketId>
            <ticketId>33</ticketId>
            <ticketId>34</ticketId>
            <ticketId>35</ticketId>
        </Tickets>
    </user>
    <user>
        <id>2</id>
        <jabber>null</jabber>
        <Vorname>Michael</Vorname>
        <Nachname>Schmidt</Nachname>
        <Standort>HAM</Standort>
        <status>user</status>
        <Tickets/>
    </user>
    <user>
        <id>3</id>
        <jabber>ollsen</jabber>
        <Vorname>Michael</Vorname>
        <Nachname>Schmidt</Nachname>
        <Standort>NBG</Standort>
        <status>supporter</status>
        <KnowHows>
            <KnowHow>Hardware</KnowHow>
            <KnowHow>Software</KnowHow>
            <KnowHow>Windows</KnowHow>
        </KnowHows>
        <Tickets>
            <ticketId>2</ticketId>
            <ticketId>3</ticketId>
            <ticketId>4</ticketId>
            <ticketId>6</ticketId>
            <ticketId>7</ticketId>
            <ticketId>8</ticketId>
            <ticketId>9</ticketId>
            <ticketId>10</ticketId>
            <ticketId>11</ticketId>
            <ticketId>12</ticketId>
            <ticketId>13</ticketId>
            <ticketId>14</ticketId>
            <ticketId>15</ticketId>
            <ticketId>16</ticketId>
            <ticketId>17</ticketId>
            <ticketId>18</ticketId>
            <ticketId>19</ticketId>
            <ticketId>20</ticketId>
            <ticketId>21</ticketId>
            <ticketId>22</ticketId>
            <ticketId>23</ticketId>
            <ticketId>24</ticketId>
            <ticketId>25</ticketId>
            <ticketId>26</ticketId>
            <ticketId>27</ticketId>
            <ticketId>28</ticketId>
            <ticketId>29</ticketId>
            <ticketId>30</ticketId>
            <ticketId>31</ticketId>
            <ticketId>32</ticketId>
            <ticketId>33</ticketId>
            <ticketId>34</ticketId>
            <ticketId>35</ticketId>
        </Tickets>
    </user>
    <user>
        <id>4</id>
        <jabber>null</jabber>
        <Vorname>Vorname</Vorname>
        <Nachname>Nachname</Nachname>
        <Standort>CGN</Standort>
        <status>supporter</status>
        <KnowHows>
            <KnowHow>Hardware</KnowHow>
            <KnowHow>Software</KnowHow>
        </KnowHows>
        <Tickets/>
    </user>
    <user>
        <id>5</id>
        <jabber>mschmidt</jabber>
        <Vorname>Michael</Vorname>
        <Nachname>Schmidt</Nachname>
        <Standort>BER</Standort>
        <status>comboBoxChanged</status>
        <KnowHows/>
        <Tickets/>
    </user>
    <user>
        <id>6</id>
        <jabber>pkrause</jabber>
        <Vorname>Petra</Vorname>
        <Nachname>Krause</Nachname>
        <Standort>CGN</Standort>
        <status>User</status>
        <KnowHows/>
        <Tickets/>
    </user>
    <user>
        <id>7</id>
        <jabber>osteinle</jabber>
        <Vorname>Oliver</Vorname>
        <Nachname>Steinle</Nachname>
        <Standort>CGN</Standort>
        <status>User</status>
        <KnowHows/>
        <Tickets/>
    </user>
</userdb>
